<?xml version="1.0" encoding="UTF-8" standalone="no"?>
<taller>
    <coche id="1">
        <marca>Tesla</marca>
    </coche>
    <coche id="2">
        <marca>BMW</marca>
    </coche>
    <coche id="3">
        <marca>BYD</marca>
    </coche>
    <coche id="4">
        <marca>Toyota</marca>
    </coche>
    <coche id="5">
        <marca>Volkswagen</marca>
    </coche>
    <coche id="6">
        <marca>Peugeot</marca>
    </coche>
    <coche id="7">
        <marca>Porsche</marca>
    </coche>
    <coche id="8">
        <marca>Ferrari</marca>
    </coche>
    <coche id="9">
        <marca>Ford</marca>
    </coche>
    <coche id="10">
        <marca>Jaguar</marca>
    </coche>
</taller>